{
  "uid": "0460D23E328D4B",
  "pages": [
    "0460D23E",
    "328D4B80",
    "74480FE0",
    "F110FFEE",
    "A5000000",
    "EEF26969",
    "A152F0C7",
    "268844AB",
    "6EC8C11A",
    "95AC4CD6",
    "AC87190F",
    "DE35213E",
    "B31FCF1D",
    "DA7DDE67",
    "1A9E14AB",
    "88FE00E6",
    "94DD3203",
    "0572BA19",
    "CD77F86D",
    "B4D3C6AD",
    "38625A49",
    "01850201",
    "01170502",
    "32313230",
    "3614BD80",
    "AD097D8B",
    "31C24C11",
    "C0708DF1",
    "83A9EF5D",
    "360A7064",
    "C45A10A2",
    "712EF3BC",
    "6EB468A2",
    "D8091DE6",
    "5415303E",
    "AFC2FC2A",
    "A9B7B919",
    "3AA5CA2C",
    "90EF0C92",
    "0F3E204C",
    "E3BD473A",
    "C4F0EFAA",
    "F26A7608",
    "1F35BC05",
    "F90550EF",
    "B3CA2663",
    "0660E224",
    "77D9C22C",
    "F5D46E5A",
    "F0E10753",
    "5CD159B1",
    "8E5B0FA7",
    "DE3D30C9",
    "1DB86689",
    "73BF9197",
    "AD21417B",
    "B8E39875",
    "52E19F05",
    "72AB2217",
    "D9773F54",
    "05814A90",
    "EAA100FD",
    "39A1EAE0",
    "4EC6173E",
    "DDF4EA25",
    "04161376",
    "732DF52C",
    "B6CEEB2F",
    "5F3D5CD8",
    "1C221898",
    "B2D74EDD",
    "C9ACC4DE",
    "6F882816",
    "E94FFCDE",
    "996AB4DC",
    "F21F0BE0",
    "BA387122",
    "E2396AAB",
    "04ED3A13",
    "CD1A8344",
    "14B1F032",
    "FFE4B06C",
    "71705D17",
    "1B779517",
    "656AC2FE",
    "D19E9AD6",
    "480C553E",
    "B8E1202C",
    "516286D9",
    "79CD3E35",
    "16820816",
    "36A6544C",
    "1072DC1D",
    "7A577382",
    "44DFA80A",
    "C19F7A2E",
    "17454F7F",
    "64AB34D7",
    "86966549",
    "70BCC88C",
    "87C2E119",
    "94C13D57",
    "6E3D1E3B",
    "9122274D",
    "20E2854A",
    "BB7B7B3D",
    "223512EF",
    "8A8A6C97",
    "7E1AD9F7",
    "046EBB2C",
    "95D1C29D",
    "39A11ACE",
    "7D111459",
    "1DDC8480",
    "F3C22D8F",
    "5BC7C9E2",
    "121EC40B",
    "E25664B7",
    "633DF13B",
    "01CF362A",
    "E3589CE3",
    "2E5D3999",
    "214CBACF",
    "68D2F239",
    "D11AAEAB",
    "A3FCE458",
    "85F2968C",
    "250BA94D",
    "6A68C1F4",
    "F5B54B7B",
    "01000FBD",
    "00000004",
    "5F000000",
    "00000000",
    "00000000"
  ],
  "metadata": {
    "original_filename": "[AC] 212 - Timmy.bin",
    "original_path": "amiibo_dumps_temp/[AC] 212 - Timmy.bin",
    "character_name": "[AC] 212 - Timmy",
    "game_series": "Animal Crossing",
    "character_id": "01850201",
    "game_id": "01170502",
    "biography": null,
    "release_date": null,
    "amiibo_type": null
  }
}