{
  "uid": "04469E54AA724C",
  "pages": [
    "04469E54",
    "AA724C80",
    "14480FE0",
    "F110FFEE",
    "A5000000",
    "12D99203",
    "6E923423",
    "55483479",
    "A8BCBE61",
    "A9BF5309",
    "0E31D8DC",
    "B5EB0E17",
    "49168783",
    "0D89684D",
    "9DBB84AA",
    "AD31BF25",
    "E88F83EE",
    "3A4443B2",
    "F0AEC576",
    "63A4B9E5",
    "56E42192",
    "01B10101",
    "017B0502",
    "33313232",
    "60B7D811",
    "DC8B0B3B",
    "374E1B6E",
    "BE41182D",
    "A31B7820",
    "F09E1966",
    "DF76663C",
    "0B523187",
    "BB610420",
    "54536374",
    "C0A22024",
    "825D3F43",
    "868ADC16",
    "B480B929",
    "2B59C4D1",
    "4823C227",
    "541847A0",
    "3562A1E7",
    "4B500944",
    "501EFF26",
    "375AC266",
    "567A037E",
    "89DBC5A2",
    "210C749F",
    "B0A4C51A",
    "80CD53CE",
    "36EA284A",
    "31C0913B",
    "9035A9B1",
    "1E3079B0",
    "3827677F",
    "2FF9A6DF",
    "BE8F10CC",
    "C0BDB79D",
    "A058EEDB",
    "153F0AE0",
    "F665D8A6",
    "6AA92CDD",
    "D14E1706",
    "D5D482F3",
    "3DBBFCF3",
    "54C51556",
    "A8AFFC7E",
    "5A183531",
    "9838C13D",
    "803DBA37",
    "FB8FD279",
    "BD981652",
    "088896FC",
    "DF635F85",
    "A9142D0B",
    "1A945854",
    "FA1FBF14",
    "0E4FEF8F",
    "CB54CA76",
    "F7C88AF8",
    "7418CC34",
    "EA637D17",
    "4CC8F6CC",
    "4DC79752",
    "1C85BE1F",
    "BB3B032A",
    "5DE59B60",
    "3C1F7A78",
    "4EF4F596",
    "4D4621BD",
    "39C80C19",
    "07A1BFEF",
    "7D2A5013",
    "B92BCD41",
    "12A4C58B",
    "B4CDC5BB",
    "70E889B6",
    "426CE2D0",
    "D27F16B5",
    "608A56D8",
    "6544A8C0",
    "6D70C84C",
    "7CD96CD6",
    "466E34E6",
    "223BEBC1",
    "F57D8FF1",
    "D5768C67",
    "EB2D4719",
    "9E670A8B",
    "78AF2310",
    "D1D28A20",
    "FC45AB73",
    "7A012392",
    "8FCC0CF6",
    "DA129C7A",
    "2AF7B275",
    "19250DE5",
    "B8D15355",
    "5EF5E1C8",
    "1D719655",
    "B4658D49",
    "04617F67",
    "9C99AB02",
    "8E090D14",
    "29C245F2",
    "25C68019",
    "69E1F453",
    "BF48DE2C",
    "C4026A2D",
    "F9E284FC",
    "01000FBD",
    "00000004",
    "5F000000",
    "00000000",
    "00000000"
  ],
  "metadata": {
    "original_filename": "[AC] 312 - Shrunk.bin",
    "original_path": "amiibo_dumps_temp/[AC] 312 - Shrunk.bin",
    "character_name": "[AC] 312 - Shrunk",
    "game_series": "Animal Crossing",
    "character_id": "01B10101",
    "game_id": "017B0502",
    "biography": null,
    "release_date": null,
    "amiibo_type": null
  }
}