{
  "uid": "042C3898BA774C",
  "pages": [
    "042C3898",
    "BA774C81",
    "00480FE0",
    "F110FFEE",
    "A5000000",
    "A181F290",
    "FAFEEA69",
    "FA0664E6",
    "8F946624",
    "516A0BED",
    "BBF3ED6F",
    "A300A3BC",
    "2B6AC6FA",
    "BEAD35A1",
    "7F039622",
    "768E23F7",
    "AC507511",
    "24C7EC46",
    "74D09944",
    "90C9F5EA",
    "1242E9C9",
    "032E0101",
    "031C0502",
    "30353432",
    "8C5BDEF3",
    "362FEC7B",
    "C70F24EA",
    "52F6F885",
    "34947738",
    "8E011127",
    "3B0F8424",
    "507AAB11",
    "D5451344",
    "6D8CACEA",
    "6DED12FD",
    "3694651A",
    "15D2041B",
    "279D7CAC",
    "966094AD",
    "6D4B7C5E",
    "9EF1DAF2",
    "009CC5E3",
    "09FB79E1",
    "28FB294F",
    "7D1F512C",
    "975772CE",
    "146B7B82",
    "0798C6F9",
    "1784C31B",
    "86EAE0D4",
    "7BB5F11F",
    "A2B4FB64",
    "1CFE997C",
    "A919E76F",
    "9599FBC8",
    "B935AAC9",
    "53535B6E",
    "7D0B796A",
    "D2577622",
    "53ABC874",
    "8F18D90B",
    "AA9636CA",
    "2DB5C4B7",
    "38B51743",
    "ED3FD7B6",
    "7CAC4E7F",
    "FC5A4AB0",
    "A0D288E7",
    "E6391C0C",
    "489FAF48",
    "FCF7C386",
    "9B61B1D5",
    "77BE904A",
    "D09BC7EF",
    "8E2C44A4",
    "5301046F",
    "C2A2D408",
    "87DF2019",
    "394FE58D",
    "F38B1A98",
    "A7B852BA",
    "48652F7F",
    "637294C6",
    "70D2D923",
    "7FEF19B4",
    "61D5B641",
    "FE5F8BB3",
    "4A0369A0",
    "EF2825B8",
    "60B71E8B",
    "C347A83E",
    "62934439",
    "755F9F7C",
    "AA29D1AB",
    "77D0D40D",
    "FF505D27",
    "5FD487FC",
    "40E1037E",
    "CF69D5BC",
    "A4B537C6",
    "2C25C71B",
    "56757AC0",
    "8898C8D4",
    "ED1EE0E6",
    "3C0D1ED4",
    "464F8EE3",
    "9FB87346",
    "E7673A1A",
    "F5647F44",
    "7EA821B7",
    "E6BA53B2",
    "CB01F728",
    "5A0EAC57",
    "B5BEAE60",
    "B06FAF41",
    "036B9B6B",
    "78D87AAC",
    "32ADC62D",
    "939C294A",
    "6CFB7300",
    "664D6954",
    "563E475D",
    "F244DA26",
    "7D6ADB37",
    "746819AA",
    "82938ADE",
    "EF43B9A6",
    "ADE6904E",
    "292DCD04",
    "8C8E8E4D",
    "01000FBD",
    "00000004",
    "5F000000",
    "00000000",
    "00000000"
  ],
  "metadata": {
    "original_filename": "[AC] XS4 - Chai.bin",
    "original_path": "amiibo_dumps_temp/[AC] XS4 - Chai.bin",
    "character_name": "[AC] XS4 - Chai",
    "game_series": "Animal Crossing",
    "character_id": "032E0101",
    "game_id": "031C0502",
    "biography": null,
    "release_date": null,
    "amiibo_type": null
  }
}