{
  "uid": "0477669D22ED49",
  "pages": [
    "0477669D",
    "22ED4981",
    "07480FE0",
    "F110FFEE",
    "A5000000",
    "0335704D",
    "15F22624",
    "83C194E4",
    "93AA67E7",
    "1961246B",
    "4A98ABC1",
    "1C7ED77C",
    "BC741358",
    "E1D2213F",
    "CBF22EF9",
    "BE126152",
    "3205D045",
    "C233EF4C",
    "AC77DCE1",
    "DE72C742",
    "8860FDD1",
    "03250001",
    "010A0502",
    "31393931",
    "27F2655A",
    "AC9B019E",
    "C9C31BDA",
    "A2131173",
    "80433044",
    "3267F0D9",
    "6F2B535B",
    "10A1B519",
    "22C16DF1",
    "7FA8606B",
    "38AC2A6B",
    "CDC29042",
    "087A68F2",
    "19A2FB2F",
    "1F7E62C8",
    "FD7978FB",
    "C4E6F57C",
    "5292D55A",
    "0251860B",
    "B582818E",
    "8907DA21",
    "BC178423",
    "0E4794E3",
    "25391239",
    "AEF2E9EE",
    "5BF24D10",
    "BEFEAE1D",
    "B4733BC7",
    "CD743544",
    "3891AD32",
    "BE67BD0A",
    "A86D10BA",
    "91669EFA",
    "380693A1",
    "90428EAD",
    "5EB7114C",
    "FC858534",
    "8C4C4E4D",
    "888AF3F0",
    "34767BD7",
    "338BB4CC",
    "FA211418",
    "FFF1BF05",
    "1F58A2C8",
    "0E9E5497",
    "AB4FFD73",
    "D5048C28",
    "E6F345F9",
    "28449C48",
    "C306224A",
    "19177F12",
    "E4A1C352",
    "B276E6CA",
    "D2A4FE17",
    "67AFABD1",
    "391E1323",
    "9177D4BF",
    "1B473478",
    "65F7FB41",
    "56934AA3",
    "4D6F62F1",
    "2BE00309",
    "F011E0A4",
    "58D8E5A8",
    "2DD33578",
    "2430B39C",
    "4F831FAE",
    "A67FD6E1",
    "EE672BAD",
    "A634ED33",
    "BA5E1057",
    "F51A9196",
    "4DF1DF90",
    "D1A8DE17",
    "F15B9105",
    "32D82A8B",
    "8503E15D",
    "CD286202",
    "87FD9FB6",
    "3F8B5290",
    "EA2FCA89",
    "F69264B1",
    "9F98BE54",
    "87935089",
    "F269BE6C",
    "AC6B8C88",
    "BD52EDAD",
    "EDF7AA2C",
    "608800C2",
    "F130BFDE",
    "656FD99C",
    "DCDE4858",
    "65AC4955",
    "8C85A012",
    "13D444BE",
    "13A12D77",
    "35BD4979",
    "D1E8037F",
    "C91D1DD8",
    "8595B588",
    "8C50D124",
    "79FD1931",
    "C595C344",
    "7B7F0D70",
    "2D2718A9",
    "7ED788B4",
    "01000FBD",
    "00000004",
    "5F000000",
    "00000000",
    "00000000"
  ],
  "metadata": {
    "original_filename": "[AC] 199 - Big Top.bin",
    "original_path": "amiibo_dumps_temp/[AC] 199 - Big Top.bin",
    "character_name": "[AC] 199 - Big Top",
    "game_series": "Animal Crossing",
    "character_id": "03250001",
    "game_id": "010A0502",
    "biography": null,
    "release_date": null,
    "amiibo_type": null
  }
}