{
  "uid": "04C4F7BFC2FE4A",
  "pages": [
    "04C4F7BF",
    "C2FE4A80",
    "F6480FE0",
    "F110FFEE",
    "A5000000",
    "B38A0124",
    "8E03D5B8",
    "1E81A3CA",
    "174076A3",
    "420E64E0",
    "7BCBA626",
    "F351EF7C",
    "C8322E32",
    "33D197CC",
    "6BC4ACE1",
    "B834C664",
    "9DE0E401",
    "CB6A46DA",
    "2370974A",
    "D569245A",
    "0121384F",
    "04A00001",
    "016E0502",
    "32393930",
    "227B7BB6",
    "E5C2860A",
    "2B95C6C7",
    "8F94CDD1",
    "9EEA323A",
    "A8074E3F",
    "86B50553",
    "AC4D033D",
    "7A16CF66",
    "C46A24E9",
    "E44B402D",
    "9D76B057",
    "7A37F57D",
    "BFB2515B",
    "27A8F771",
    "9CE923F0",
    "746EB946",
    "FC23D21B",
    "DD3BD7EA",
    "030249E0",
    "29EDCA37",
    "B3DAD441",
    "5D5FF6DC",
    "EA735A45",
    "2AF03348",
    "CB6EC2A5",
    "67C73C05",
    "26581C30",
    "ED55808C",
    "E81151E7",
    "D4AD06CF",
    "655BC1F3",
    "21197294",
    "5FBC407D",
    "0FB531A4",
    "AF67CEF7",
    "D988C573",
    "23B98F5F",
    "426CBCBC",
    "A8AFAE1A",
    "C1AF4DB9",
    "D8DFA9E3",
    "E3804DE5",
    "4F0777BE",
    "F9FE7726",
    "F0146EDB",
    "A10F0FDF",
    "30F21C35",
    "DC08B93A",
    "B15B7669",
    "E2C9B461",
    "A3BCB537",
    "1CA1AA4B",
    "0A5A193D",
    "F2B0BA89",
    "BCF91FE5",
    "487D9ACF",
    "7759A81E",
    "EA5EC2D7",
    "0382851A",
    "736AC2D8",
    "C72CCE8E",
    "CE2F4C24",
    "36D61AF1",
    "29077FA6",
    "0989048D",
    "CFABB178",
    "5339A858",
    "F4F88723",
    "E6D1EC38",
    "7C9BB0C8",
    "D2107CD5",
    "CD75BAF0",
    "BB33B130",
    "3A445A48",
    "5A2D93DC",
    "B38BB473",
    "5CD7E5A9",
    "83ABB926",
    "50E80F75",
    "D2D4BD06",
    "087A60FB",
    "511B869A",
    "181655AE",
    "042166B1",
    "495E56D1",
    "37EB6DD8",
    "4E380998",
    "D71CDA9C",
    "AEB9C30F",
    "09627FE5",
    "9938B83A",
    "630DF2DF",
    "29FC17A5",
    "E6734AC6",
    "90D2DB91",
    "BE4AD848",
    "3219E4F2",
    "A65963C8",
    "2CBBE198",
    "F174D4DE",
    "A4852946",
    "DC8D2F5E",
    "E6965E37",
    "CC27771F",
    "070789D7",
    "01000FBD",
    "00000004",
    "5F000000",
    "00000000",
    "00000000"
  ],
  "metadata": {
    "original_filename": "[AC] 299 - Francine.bin",
    "original_path": "amiibo_dumps_temp/[AC] 299 - Francine.bin",
    "character_name": "[AC] 299 - Francine",
    "game_series": "Animal Crossing",
    "character_id": "04A00001",
    "game_id": "016E0502",
    "biography": null,
    "release_date": null,
    "amiibo_type": null
  }
}