{
  "uid": "0431BC0122ED49",
  "pages": [
    "0431BC01",
    "22ED4981",
    "07480FE0",
    "F110FFEE",
    "A5000000",
    "B8F436FB",
    "A66B2369",
    "022A131D",
    "2A774C4E",
    "D7D51E37",
    "3FE7838C",
    "3FFECFC3",
    "3445C0AE",
    "B71823E5",
    "76BEC688",
    "37E74E09",
    "54306D0D",
    "627EF797",
    "90974064",
    "73AA3311",
    "D0325800",
    "026E0001",
    "00BA0502",
    "31313930",
    "43BBB2B4",
    "2F83D055",
    "E5608B90",
    "D5037466",
    "5E93D67B",
    "C4B0DF1A",
    "CE47B54F",
    "BD1BFC0F",
    "63F0356C",
    "801157B1",
    "D6F911F2",
    "AFB532B8",
    "5EB31EC2",
    "3E3FA005",
    "A2C512F9",
    "2B786D74",
    "A54AAF3C",
    "BBF05F50",
    "4064C838",
    "21F02443",
    "64092A9A",
    "27506DBD",
    "3A2E3EC1",
    "DD5E0A66",
    "9AA54B62",
    "7B432B2A",
    "17A79B61",
    "50AE2D55",
    "7240DA5C",
    "C6FDA85E",
    "D680E728",
    "48E51F48",
    "CC0181C1",
    "340EFCFE",
    "D5636C54",
    "678C70C3",
    "12EC4BA4",
    "E046B546",
    "4B08ECD2",
    "B4AC9366",
    "B1E081D7",
    "5F1CC658",
    "2B2B9A76",
    "9886F0EF",
    "A274D5C4",
    "1EF2BE3A",
    "C835CC1B",
    "E3BCBAF9",
    "AEC6B4A9",
    "3E9F82AE",
    "A1EE2367",
    "BA8D465B",
    "3D7BEFB2",
    "876825EA",
    "D95542C8",
    "497186D2",
    "00347AB8",
    "66DA1DF4",
    "42FF509D",
    "8A3DDA2D",
    "4CC2F854",
    "15D5C1DF",
    "DF9CFB6C",
    "08013758",
    "3878C572",
    "D14EA171",
    "A9240CE8",
    "C75CC466",
    "461B8D04",
    "2A62C3F6",
    "F8363A58",
    "9FF83823",
    "9E9FBDF9",
    "C6986DB5",
    "77856609",
    "F681A709",
    "48443FB1",
    "337A10E7",
    "139BA0D9",
    "ADDF4EB1",
    "2E98F8A3",
    "654AE56B",
    "C085408A",
    "958E2121",
    "CC1E99D6",
    "D50F28C2",
    "C5BFF35B",
    "A3705665",
    "1DCBF45B",
    "6636A355",
    "E9E85C81",
    "A42610C0",
    "4FE808E0",
    "64211C12",
    "3D8F4F75",
    "99EC1EC1",
    "56978A02",
    "6209EE4F",
    "30BAD37D",
    "0AD1C3EF",
    "208ABD94",
    "9DD53FD8",
    "B779A7D6",
    "F4A7DAE8",
    "02661DA2",
    "FE37E973",
    "01000FBD",
    "00000004",
    "5F000000",
    "00000000",
    "00000000"
  ],
  "metadata": {
    "original_filename": "[AC] 119 - Felicity.bin",
    "original_path": "amiibo_dumps_temp/[AC] 119 - Felicity.bin",
    "character_name": "[AC] 119 - Felicity",
    "game_series": "Animal Crossing",
    "character_id": "026E0001",
    "game_id": "00BA0502",
    "biography": null,
    "release_date": null,
    "amiibo_type": null
  }
}