{
  "uid": "04F7CAB1CA6F73",
  "pages": [
    "04F7CAB1",
    "CA6F7380",
    "56480FE0",
    "F110FFEE",
    "A5000000",
    "B3000402",
    "2E0F3132",
    "12A2A956",
    "AE7E1C7C",
    "C774B1DD",
    "B29022A9",
    "C9857030",
    "2CF93550",
    "9089D356",
    "32D9F383",
    "656E4725",
    "435C3F21",
    "35710F7C",
    "F46965E9",
    "37E19E36",
    "8C6C37DA",
    "0A1B0001",
    "03D20502",
    "39313131",
    "4C703882",
    "7555442B",
    "5D81CFB1",
    "4EF09266",
    "A7D59629",
    "AEB35403",
    "8A8989A4",
    "3CD7CA37",
    "62B40744",
    "C23A8D6A",
    "5980E045",
    "397B838C",
    "48CFC6CE",
    "7B3C1B89",
    "93427792",
    "91354408",
    "8E93BF58",
    "D5882294",
    "60BDDF68",
    "354F2C3B",
    "22CCDDCC",
    "4EBFEC5F",
    "0B2809D9",
    "256C3AE2",
    "CF7EB8C7",
    "EE6917F3",
    "C9B2FD15",
    "F3ADDFD7",
    "426ABBF7",
    "2D68386E",
    "0732E2E4",
    "CEEFB40C",
    "81680C52",
    "2084B727",
    "247C1F86",
    "C83C8DB6",
    "A0A924A9",
    "F7782F12",
    "EDDF23A4",
    "CEBCEE42",
    "876FB878",
    "35D49C0F",
    "4C0F60E5",
    "A22CBB2A",
    "7C57CE9C",
    "9C42831B",
    "4A54CB52",
    "F6FCE72E",
    "96F334CF",
    "D40BB377",
    "0ACF16D0",
    "CEE9AF51",
    "4D3FC9B9",
    "10008DB6",
    "12EE7054",
    "82D23BBF",
    "BC8E84CF",
    "C8122C76",
    "F7190245",
    "D04FAC81",
    "0883BA08",
    "A71282E3",
    "521075BE",
    "AD70F1DE",
    "166731C7",
    "1AB9D2FE",
    "3A5FABD2",
    "7D330D65",
    "8ED82CBD",
    "EE0FDC39",
    "FE6006A2",
    "D0C5AB2A",
    "52E3FBA8",
    "06B21697",
    "7A5F2F18",
    "42C0D040",
    "D124B3A8",
    "ADEF88F0",
    "0BF7B4F9",
    "B5EB9BE0",
    "D6085399",
    "75590BDC",
    "514161FA",
    "B0D5E5F8",
    "AD769DF4",
    "51A73C39",
    "2245FA43",
    "8B6EBFE0",
    "8732306F",
    "7C2150E3",
    "517B825D",
    "EF0ED7DC",
    "8741045E",
    "56854135",
    "7594AFC0",
    "78A44DF0",
    "C412052E",
    "2DB7F755",
    "DBA5692D",
    "89D831DD",
    "CF14EF57",
    "35E53D1D",
    "29203B9F",
    "2B2DDCCA",
    "36FCF31D",
    "D63CC6F2",
    "01000FBD",
    "00000004",
    "5F000000",
    "00000000",
    "00000000"
  ],
  "metadata": {
    "original_filename": "443 - Ace.bin",
    "original_path": "amiibo_dumps_temp/443 - Ace.bin",
    "character_name": "443 - Ace",
    "game_series": "Unknown",
    "character_id": "0A1B0001",
    "game_id": "03D20502",
    "biography": null,
    "release_date": null,
    "amiibo_type": null
  }
}