{
  "uid": "04942931CBF440",
  "pages": [
    "04942931",
    "CBF44080",
    "FF480FE0",
    "F110FFEE",
    "A5000300",
    "28C5C9FB",
    "523AFCC7",
    "B7BF278A",
    "A183D57D",
    "C4E966AD",
    "12B26619",
    "26AFF307",
    "9214057F",
    "73EBE7B7",
    "C7840042",
    "103C5DAD",
    "7868069F",
    "16FDAE67",
    "BC44F21D",
    "F4F06004",
    "EA8CE09E",
    "026A0001",
    "00000502",
    "30303130",
    "62CCE919",
    "FC57B6CC",
    "23EDF768",
    "BA659EE8",
    "4A994D14",
    "C0B103CA",
    "507BF671",
    "A3BAE924",
    "9481D747",
    "6C22FC7C",
    "ACEECABB",
    "4446BDB7",
    "07395CC2",
    "335E3A27",
    "F456D16C",
    "E69698F9",
    "E4E35083",
    "004B2D79",
    "CD0C2C06",
    "180A9569",
    "A8989C98",
    "8E610BDA",
    "3174B94B",
    "A54E6099",
    "C28FAA76",
    "F7531086",
    "ABDEE823",
    "0E587CD8",
    "6F7D22AD",
    "86DA7CB5",
    "C1D5958E",
    "847C6E12",
    "F4B87EF0",
    "F5A95201",
    "BCACEE58",
    "2EE8D68D",
    "60EE1F66",
    "BCC6C9C9",
    "57970178",
    "87708FDD",
    "134A5004",
    "FED47110",
    "E39A702D",
    "527FACD9",
    "C2F321F8",
    "2BA92632",
    "3359C288",
    "6542F17B",
    "944B3786",
    "2E788CCA",
    "CA47D9FB",
    "BA186FFE",
    "FC1F48E3",
    "EE1D4757",
    "43DB7E09",
    "26B39C70",
    "9258636C",
    "342AECC4",
    "D6BFEAD3",
    "13FF508D",
    "C2F1797D",
    "5A7092B2",
    "F30223DD",
    "B78F5E5A",
    "71443F8C",
    "0C45102F",
    "7A0E9A18",
    "FFE61E1D",
    "B4940993",
    "B388390D",
    "A8C1EBCC",
    "69B1FE7C",
    "63D62F2B",
    "FCBB237D",
    "62286CA6",
    "19833378",
    "EA6A783B",
    "7F58553E",
    "4536C68A",
    "33A4E532",
    "DFDDA38D",
    "18F89C00",
    "90508B97",
    "CB0E58A1",
    "97E27663",
    "C16A8D9C",
    "284A8FBF",
    "F90511A1",
    "BF66B3F8",
    "95EF589E",
    "F395262F",
    "F7E57F77",
    "1D8F9A45",
    "881572D2",
    "3DF44118",
    "A45DF4E2",
    "667AEB9E",
    "34E24166",
    "41073C70",
    "E65AAD54",
    "A7AB096D",
    "2D89FCA2",
    "BA79D76F",
    "7FACA791",
    "48DE9BAC",
    "EA67C297",
    "01000FBD",
    "00000004",
    "5F000000",
    "00000000",
    "00000000"
  ],
  "metadata": {
    "original_filename": "[HHD] Items - 56.bin",
    "original_path": "amiibo_dumps_temp/[HHD] Items - 56.bin",
    "character_name": "[HHD] Items - 56",
    "game_series": "Unknown",
    "character_id": "026A0001",
    "game_id": "00000502",
    "biography": null,
    "release_date": null,
    "amiibo_type": null
  }
}