{
  "uid": "042AF355EA9A3D",
  "pages": [
    "042AF355",
    "EA9A3D81",
    "CC480FE0",
    "F110FFEE",
    "A5000000",
    "C12CB3C4",
    "DEFCB228",
    "962C6765",
    "F2C27196",
    "4DACB9B7",
    "8DE90D46",
    "9D4366B4",
    "55FC63F2",
    "660E8EB6",
    "52F9E50F",
    "C4421511",
    "6E52A37D",
    "40B96AB0",
    "925ED8A1",
    "3A477505",
    "D1A56F39",
    "1F000000",
    "000A0002",
    "0512A407",
    "A2ECE30B",
    "2AA57737",
    "4932D199",
    "F430997A",
    "A4DB3402",
    "E6972674",
    "E3037E63",
    "7E82EE26",
    "FD677933",
    "1BFE6030",
    "A10584C5",
    "66563FDB",
    "C093E122",
    "43906674",
    "F1F34F24",
    "745AE886",
    "515CB1D3",
    "BB57A8F6",
    "0059DB3C",
    "63041E3F",
    "C9E3B5EF",
    "A3C7F963",
    "2A8BBE00",
    "05DA7A37",
    "3D1F7630",
    "56A45F39",
    "94A28869",
    "A1EDDDA4",
    "0D017D4F",
    "78F91259",
    "4A37D1D9",
    "7120EE53",
    "1C973A3A",
    "D0D93074",
    "1FEC658D",
    "1C7A06B1",
    "63B50CA6",
    "4DEA2B91",
    "DC286BE0",
    "5C2AF16A",
    "5F293B1F",
    "1DD8F746",
    "A30C4CC2",
    "CE0F9227",
    "63667510",
    "D32512B9",
    "7FBD3EA4",
    "63FAD8D8",
    "F4EDB74E",
    "151C04A7",
    "018D41B5",
    "3E511889",
    "8895D2E8",
    "B985FD0F",
    "9C3104C1",
    "DB71FAA4",
    "26918769",
    "B81742EA",
    "31EA7F12",
    "426F7BFF",
    "4E7A3AD2",
    "E7145F8B",
    "5332BA04",
    "1533DBAC",
    "F2346426",
    "BA8A1AD1",
    "65684BF9",
    "6AE1CA73",
    "1BCE203C",
    "13A49CCA",
    "1B61B270",
    "832124C5",
    "0193704B",
    "EFDEFF15",
    "F160538C",
    "9727A89D",
    "7D419236",
    "756293D0",
    "10626417",
    "B6AA49B8",
    "B2118293",
    "39BEF35C",
    "CF3E2CC6",
    "F46B52AB",
    "B47C102B",
    "D2934385",
    "135690D2",
    "6812C298",
    "1E87AE2A",
    "EDAAEF4A",
    "7486C9C2",
    "52469CA5",
    "A71F84C0",
    "914C9148",
    "F351BF9A",
    "DB8ACF26",
    "6594E7D2",
    "D4D7D12C",
    "5D6684E3",
    "61CBCFA3",
    "2B07F026",
    "13939D48",
    "8B98E83A",
    "5E5CDD07",
    "0387F726",
    "DB8873F7",
    "01000FBD",
    "00000004",
    "5F000000",
    "00000000",
    "00000000"
  ],
  "metadata": {
    "original_filename": "Kirby.bin",
    "original_path": "amiibo_dumps_temp/Kirby.bin",
    "character_name": "Kirby",
    "game_series": "Super Smash Bros.",
    "character_id": "1F000000",
    "game_id": "000A0002",
    "biography": null,
    "release_date": null,
    "amiibo_type": null
  }
}