{
  "uid": "0468CB2F727C11",
  "pages": [
    "0468CB2F",
    "727C1190",
    "8F480FE0",
    "F110FFEE",
    "A5000000",
    "40ED019B",
    "1A966EB5",
    "F2E0F0FE",
    "388C7173",
    "157BC549",
    "CCBB62E7",
    "28E522C0",
    "7764FADA",
    "0E5B9EB1",
    "6784B7BC",
    "ED11E115",
    "4FE94055",
    "86327B75",
    "FCD782C8",
    "6643595E",
    "C0E4F202",
    "01000000",
    "04180902",
    "0D12B212",
    "AB7566DF",
    "9470C5AD",
    "379E98BD",
    "78C48A88",
    "5F3E16C7",
    "EED187B4",
    "973A0D94",
    "FEAE8329",
    "E83631D3",
    "A4677419",
    "1DA8CF90",
    "3588A07E",
    "D86C2850",
    "FF4496EC",
    "A29CFAE5",
    "E9A9F6EE",
    "684A8353",
    "9839F9F7",
    "83A78438",
    "93C2E63F",
    "66C5A324",
    "B61DBB77",
    "5F44890A",
    "BA1C5FEA",
    "E9E3D793",
    "B9980691",
    "4C5B176F",
    "38798C22",
    "ABCE1ED8",
    "0F8B18DE",
    "7DDA3DEB",
    "42E28372",
    "DC0EC261",
    "6C8CB8FC",
    "D284A4A7",
    "AE3F4A2A",
    "865D595F",
    "095B1C62",
    "7FCE04C1",
    "9622A0B8",
    "CE77334D",
    "F45BB3A4",
    "D297F677",
    "2E5D21B4",
    "1E098930",
    "60087E67",
    "EF6764AE",
    "F80A2A9D",
    "1CBC8231",
    "AB5F7A29",
    "CD874014",
    "75680EB9",
    "DFAEAB2F",
    "BCC5D2E2",
    "3C6F145D",
    "20165146",
    "4086C2A9",
    "9F6D2842",
    "B8F825DF",
    "35632D1A",
    "5380B3D2",
    "48DC683C",
    "5384C5E9",
    "DA63E9B8",
    "0327773B",
    "5B17A64F",
    "A6689841",
    "AD3DC622",
    "26C1479A",
    "62112AA0",
    "B5C58ADA",
    "C799B6E8",
    "69B18A21",
    "3E5D29D7",
    "49B5CC97",
    "6D613E55",
    "7F091750",
    "2649EA97",
    "C491C6DA",
    "E9AD4346",
    "EDAE3225",
    "C904B921",
    "8F1076FE",
    "3090D1AE",
    "7B422DC4",
    "9E8C6DA1",
    "215DC524",
    "B92BF227",
    "0E0465B2",
    "00D95142",
    "209B3040",
    "B81EC5E7",
    "F4A57391",
    "FC9A6CD6",
    "8EEC192D",
    "1BDEA10D",
    "909EF327",
    "4DCFCA0B",
    "1702A2EF",
    "59D65F26",
    "98351B36",
    "66419A65",
    "25A60384",
    "44176B9D",
    "CE731F78",
    "AA19C76F",
    "01000FBD",
    "00000004",
    "5F000000",
    "00000000",
    "00000000"
  ],
  "metadata": {
    "original_filename": "Link (TotK).bin",
    "original_path": "amiibo_dumps_temp/Link (TotK).bin",
    "character_name": "Link (TotK)",
    "game_series": "Super Smash Bros.",
    "character_id": "01000000",
    "game_id": "04180902",
    "biography": null,
    "release_date": null,
    "amiibo_type": null
  }
}