{
  "uid": "040821A532124A",
  "pages": [
    "040821A5",
    "32124A81",
    "EB480FE0",
    "F110FFEE",
    "A59DC700",
    "7B7D2D20",
    "39FF790A",
    "EE8B3DE5",
    "78888D35",
    "7C6A4D3D",
    "96291A6B",
    "3FAA0D6D",
    "408AA3B1",
    "21A28838",
    "496D784E",
    "D1715231",
    "ACA56332",
    "EF31662D",
    "5E560C46",
    "45A07901",
    "7D39D0CE",
    "22810000",
    "02510002",
    "0D12B511",
    "BA8C98AB",
    "D54CBDCD",
    "98DCCA51",
    "1BD6448F",
    "7D1D5114",
    "220BE577",
    "7F194559",
    "3884003F",
    "7A8ADA7B",
    "77FA104B",
    "5719FF10",
    "24CDF0C8",
    "4784D7F4",
    "2E6888C1",
    "6C20A0EA",
    "2CF524E1",
    "F90F301F",
    "0EC08B27",
    "81EAB109",
    "F149D349",
    "CFD34BCC",
    "0E789D25",
    "8D2197ED",
    "FA61AFD8",
    "F62FAAF9",
    "346848FB",
    "53465D77",
    "FBF17124",
    "8D6D96CD",
    "62AEEE55",
    "FB96212E",
    "8C9F2721",
    "F8E4038F",
    "8DA71218",
    "F2298F8A",
    "207F794D",
    "AE40472E",
    "8CF7FF2A",
    "909FDEE3",
    "4D3927D7",
    "4957DDB7",
    "0A2BF995",
    "E754704F",
    "58FB4947",
    "1F26015E",
    "A58832FE",
    "EF8B9433",
    "9460E96F",
    "5C1AEFFA",
    "8803BE07",
    "D6F5E3D8",
    "D6B0ABED",
    "2D6DBF91",
    "A71234B3",
    "98DB7B6A",
    "53F35E66",
    "27CE4BB7",
    "A2EB4433",
    "2C8F5271",
    "30954449",
    "D4BD1B98",
    "85E9991C",
    "CA6A1655",
    "6860A4D7",
    "2D7330AB",
    "D1A85529",
    "0D15CD26",
    "F8992242",
    "22E975D1",
    "EE9EAD14",
    "2B10CA5A",
    "480C6F09",
    "E45D6042",
    "7176CBF1",
    "2F58D886",
    "14016449",
    "32ED8A30",
    "356A8AA8",
    "A36A2A2C",
    "409AF5DC",
    "A8262779",
    "C55D952C",
    "BEDC44D9",
    "ADF3156F",
    "20629E25",
    "75C6AD4F",
    "2195F8E1",
    "86A302C1",
    "F2A18EC9",
    "0A21750D",
    "5940AB95",
    "CBEB44B8",
    "D6725F1F",
    "599876F6",
    "F5C99406",
    "43B236CB",
    "7A2A22AF",
    "D471CD6B",
    "018A196B",
    "59F88ECA",
    "E47ECD96",
    "00F7B584",
    "8643A1D3",
    "1A1F12DF",
    "7ABEACC6",
    "58D46AA6",
    "01000FBD",
    "00000004",
    "5F000000",
    "00000000",
    "00000000"
  ],
  "metadata": {
    "original_filename": "Lucas.bin",
    "original_path": "amiibo_dumps_temp/Lucas.bin",
    "character_name": "Lucas",
    "game_series": "Super Smash Bros.",
    "character_id": "22810000",
    "game_id": "02510002",
    "biography": null,
    "release_date": null,
    "amiibo_type": null
  }
}