{
  "uid": "04415994CAE049",
  "pages": [
    "04415994",
    "CAE04981",
    "E2480FE0",
    "F110FFEE",
    "A5000100",
    "E01C6FDA",
    "387A199A",
    "4A3717E0",
    "9620B5DC",
    "A4A29FB2",
    "8A27FEEF",
    "282DC1C3",
    "853FCAEF",
    "82A98846",
    "6EDBE97E",
    "8366E82D",
    "27A5DBB5",
    "08B3F0E7",
    "99C839F4",
    "4B914B80",
    "3E61A467",
    "00140000",
    "02670102",
    "0D126611",
    "4638E847",
    "8A87DB55",
    "3253C7A1",
    "375E5601",
    "487D4C01",
    "18D306AC",
    "E0BF21F9",
    "95449E0C",
    "B2B82BFA",
    "4036BCE8",
    "DD015623",
    "C8E3A566",
    "04961FAE",
    "C81FEE18",
    "9094C425",
    "E417A4EC",
    "1EE56FCF",
    "9C86819A",
    "6C2412FF",
    "8B775890",
    "AEEA59C5",
    "C102BB98",
    "2B897E6B",
    "09722839",
    "F147624D",
    "7CA627D4",
    "F2C45D01",
    "ACE30B70",
    "221AF4ED",
    "423C0BAA",
    "17D72828",
    "1E2FF160",
    "93BD42B9",
    "44B80266",
    "FFAC0B71",
    "851CBB2C",
    "66BAB51F",
    "9B071515",
    "6E678824",
    "4E975935",
    "44411D4D",
    "35EE23A0",
    "FEE2E2CC",
    "93CFF1CA",
    "76B013F2",
    "496ED55A",
    "64889727",
    "D5BA05CF",
    "362B7A7B",
    "AE436F43",
    "595A0F6E",
    "30AE96C5",
    "7F7E5DC8",
    "951A9A48",
    "A02A6A73",
    "80DD44BB",
    "8737E2DD",
    "4BE6837F",
    "0963224A",
    "3CC91441",
    "552A86DD",
    "25281FCC",
    "BCC4D663",
    "8BA6A7EB",
    "A8F4E4AE",
    "F8DA75FB",
    "01B97AD2",
    "6FBB5B95",
    "D27FADA8",
    "0848A077",
    "B4C3456A",
    "9D1F0503",
    "ECA3CDD5",
    "1443C91F",
    "C470F99C",
    "35EBE5DC",
    "1D726994",
    "AECE40C4",
    "1D533EEA",
    "1CF62C3A",
    "C15B382D",
    "AFEFE4FB",
    "64AE5E82",
    "5B58F2CD",
    "545DD56B",
    "214C250A",
    "46976C33",
    "84637A00",
    "0675498B",
    "487FC0E3",
    "4447889C",
    "265709C4",
    "F2AFC489",
    "52DD682D",
    "2CCBED87",
    "76B60E45",
    "7F67FF41",
    "28ABAE66",
    "E5C8E2B9",
    "5A1B6BCB",
    "C68C6110",
    "9FBA1DE5",
    "334D6491",
    "A7B21481",
    "AC31DAF1",
    "41D3FDC2",
    "01000FBD",
    "00000004",
    "5F000000",
    "00000000",
    "00000000"
  ],
  "metadata": {
    "original_filename": "Waluigi.bin",
    "original_path": "amiibo_dumps_temp/Waluigi.bin",
    "character_name": "Waluigi",
    "game_series": "Super Smash Bros.",
    "character_id": "00140000",
    "game_id": "02670102",
    "biography": null,
    "release_date": null,
    "amiibo_type": null
  }
}